ccux/__init__.py
ccux/__main__.py
ccux/cli.py
ccux/cli_old.py
ccux/interactive.py
ccux/multipage.py
ccux/prompt_templates.py
ccux/scrape.py
ccux/scrape_simple.py
ccux/theme_specifications.py
ccux/core/README.md
ccux/core/__init__.py
ccux/core/animation_utilities.py
ccux/core/claude_integration.py
ccux/core/configuration.py
ccux/core/content_processing.py
ccux/core/form_handling.py
ccux/core/navigation_builder.py
ccux/core/page_analysis.py
ccux/core/page_selection.py
ccux/core/parallel_generator.py
ccux/core/project_management.py
ccux/core/retry_handler.py
ccux/core/section_management.py
ccux/core/signal_handling.py
ccux/core/sitemap_generator.py
ccux/core/usage_tracking.py
ccux-4.1.1.dist-info/METADATA
ccux-4.1.1.dist-info/WHEEL
ccux-4.1.1.dist-info/entry_points.txt
ccux-4.1.1.dist-info/RECORD
