Metadata-Version: 2.4
Name: ccux
Version: 4.1.1
Summary: A sophisticated Python CLI tool that automatically generates conversion-optimized frontend landing pages using professional UX design thinking methodology
Author: CCUX Team
License: MIT
Keywords: ai,claude,design,frontend,generator,landing-page,ui,ux
Classifier: Development Status :: 4 - Beta
Classifier: Intended Audience :: Developers
Classifier: License :: OSI Approved :: MIT License
Classifier: Operating System :: OS Independent
Classifier: Programming Language :: Python :: 3
Classifier: Programming Language :: Python :: 3.9
Classifier: Programming Language :: Python :: 3.10
Classifier: Programming Language :: Python :: 3.11
Classifier: Programming Language :: Python :: 3.12
Classifier: Topic :: Internet :: WWW/HTTP :: Dynamic Content
Classifier: Topic :: Software Development :: Code Generators
Classifier: Topic :: Software Development :: User Interfaces
Requires-Python: >=3.9
Requires-Dist: playwright>=1.45.0
Requires-Dist: pypdf2>=3.0.0
Requires-Dist: pyyaml>=6.0.1
Requires-Dist: rich>=13.7.0
Requires-Dist: typer>=0.12.0
